{
	"info": {
		"_postman_id": "deskly-api-collection",
		"name": "Deskly E-commerce API",
		"description": "Coleção completa de endpoints da API Deskly",
		"schema": "https://schema.getpostman.com/json/collection/v2.1.0/collection.json"
	},
	"item": [
		{
			"name": "Auth",
			"item": [
				{
					"name": "Login",
					"event": [
						{
							"listen": "test",
							"script": {
								"exec": [
									"if (pm.response.code === 200) {",
									"    const response = pm.response.json();",
									"    pm.environment.set(\"token\", response.token);",
									"}"
								],
								"type": "text/javascript"
							}
						}
					],
					"request": {
						"method": "POST",
						"header": [
							{
								"key": "Content-Type",
								"value": "application/json"
							}
						],
						"body": {
							"mode": "raw",
							"raw": "{\n    \"email\": \"admin@deskly.com\",\n    \"password\": \"admin123\"\n}"
						},
						"url": {
							"raw": "{{baseUrl}}/auth/login",
							"host": [
								"{{baseUrl}}"
							],
							"path": [
								"auth",
								"login"
							]
						}
					},
					"response": []
				},
				{
					"name": "Register",
					"event": [
						{
							"listen": "test",
							"script": {
								"exec": [
									"if (pm.response.code === 200) {",
									"    const response = pm.response.json();",
									"    pm.environment.set(\"token\", response.token);",
									"}"
								],
								"type": "text/javascript"
							}
						}
					],
					"request": {
						"method": "POST",
						"header": [
							{
								"key": "Content-Type",
								"value": "application/json"
							}
						],
						"body": {
							"mode": "raw",
							"raw": "{\n    \"fullname\": \"João Silva\",\n    \"email\": \"joao.silva@email.com\",\n    \"cpf\": \"12345678901\",\n    \"password\": \"senha123\",\n    \"confirmPassword\": \"senha123\",\n    \"role\": \"CLIENTE\"\n}"
						},
						"url": {
							"raw": "{{baseUrl}}/auth/register",
							"host": [
								"{{baseUrl}}"
							],
							"path": [
								"auth",
								"register"
							]
						}
					},
					"response": []
				}
			]
		},
		{
			"name": "User",
			"item": [
				{
					"name": "Create User",
					"request": {
						"method": "POST",
						"header": [
							{
								"key": "Content-Type",
								"value": "application/json"
							},
							{
								"key": "Authorization",
								"value": "Bearer {{token}}"
							}
						],
						"body": {
							"mode": "raw",
							"raw": "{\n    \"fullname\": \"Maria Santos\",\n    \"email\": \"maria.santos@email.com\",\n    \"cpf\": \"98765432100\",\n    \"password\": \"senha123\",\n    \"confirmPassword\": \"senha123\",\n    \"role\": \"CLIENTE\"\n}"
						},
						"url": {
							"raw": "{{baseUrl}}/users",
							"host": [
								"{{baseUrl}}"
							],
							"path": [
								"users"
							]
						}
					},
					"response": []
				},
				{
					"name": "Update User",
					"request": {
						"method": "PUT",
						"header": [
							{
								"key": "Content-Type",
								"value": "application/json"
							},
							{
								"key": "Authorization",
								"value": "Bearer {{token}}"
							}
						],
						"body": {
							"mode": "raw",
							"raw": "{\n    \"fullname\": \"Maria Santos Silva\",\n    \"cpf\": \"98765432100\",\n    \"password\": \"novaSenha123\",\n    \"confirmPassword\": \"novaSenha123\",\n    \"role\": \"CLIENTE\"\n}"
						},
						"url": {
							"raw": "{{baseUrl}}/users/:id",
							"host": [
								"{{baseUrl}}"
							],
							"path": [
								"users",
								":id"
							],
							"variable": [
								{
									"key": "id",
									"value": "1"
								}
							]
						}
					},
					"response": []
				}
			]
		},
		{
			"name": "Product",
			"item": [
				{
					"name": "Create Product",
					"request": {
						"method": "POST",
						"header": [
							{
								"key": "Content-Type",
								"value": "application/json"
							},
							{
								"key": "Authorization",
								"value": "Bearer {{token}}"
							}
						],
						"body": {
							"mode": "raw",
							"raw": "{\n    \"name\": \"Mouse Gamer RGB\",\n    \"description\": \"Mouse gamer com iluminação RGB personalizável\",\n    \"price\": 149.90,\n    \"rating\": 4.5,\n    \"quantity\": 50,\n    \"productImage\": \"data:image/jpeg;base64,/9j/4AAQSkZJRg...\"\n}"
						},
						"url": {
							"raw": "{{baseUrl}}/products",
							"host": [
								"{{baseUrl}}"
							],
							"path": [
								"products"
							]
						}
					},
					"response": []
				},
				{
					"name": "List Products",
					"request": {
						"method": "GET",
						"header": [
							{
								"key": "Authorization",
								"value": "Bearer {{token}}"
							}
						],
						"url": {
							"raw": "{{baseUrl}}/products?page=0&size=10",
							"host": [
								"{{baseUrl}}"
							],
							"path": [
								"products"
							],
							"query": [
								{
									"key": "page",
									"value": "0"
								},
								{
									"key": "size",
									"value": "10"
								},
								{
									"key": "search",
									"value": "mouse",
									"disabled": true
								}
							]
						}
					},
					"response": []
				},
				{
					"name": "Get Product by ID",
					"request": {
						"method": "GET",
						"header": [
							{
								"key": "Authorization",
								"value": "Bearer {{token}}"
							}
						],
						"url": {
							"raw": "{{baseUrl}}/products/:id",
							"host": [
								"{{baseUrl}}"
							],
							"path": [
								"products",
								":id"
							],
							"variable": [
								{
									"key": "id",
									"value": "1"
								}
							]
						}
					},
					"response": []
				},
				{
					"name": "Update Product",
					"request": {
						"method": "PUT",
						"header": [
							{
								"key": "Content-Type",
								"value": "application/json"
							},
							{
								"key": "Authorization",
								"value": "Bearer {{token}}"
							}
						],
						"body": {
							"mode": "raw",
							"raw": "{\n    \"name\": \"Mouse Gamer RGB Pro\",\n    \"price\": 179.90,\n    \"productImage\": \"data:image/jpeg;base64,/9j/4AAQSkZJRg...\"\n}"
						},
						"url": {
							"raw": "{{baseUrl}}/products/:id",
							"host": [
								"{{baseUrl}}"
							],
							"path": [
								"products",
								":id"
							],
							"variable": [
								{
									"key": "id",
									"value": "1"
								}
							]
						}
					},
					"response": []
				},
				{
					"name": "Toggle Product Status",
					"request": {
						"method": "PATCH",
						"header": [
							{
								"key": "Authorization",
								"value": "Bearer {{token}}"
							}
						],
						"url": {
							"raw": "{{baseUrl}}/products/:id/status?active=true",
							"host": [
								"{{baseUrl}}"
							],
							"path": [
								"products",
								":id",
								"status"
							],
							"query": [
								{
									"key": "active",
									"value": "true"
								}
							],
							"variable": [
								{
									"key": "id",
									"value": "1"
								}
							]
						}
					},
					"response": []
				}
			]
		}
	],
	"event": [
		{
			"listen": "prerequest",
			"script": {
				"type": "text/javascript",
				"exec": [
					""
				]
			}
		},
		{
			"listen": "test",
			"script": {
				"type": "text/javascript",
				"exec": [
					""
				]
			}
		}
	],
	"variable": [
		{
			"key": "baseUrl",
			"value": "http://localhost:8080",
			"type": "string"
		},
		{
			"key": "token",
			"value": "",
			"type": "string"
		}
	]
}
